multisubprocess/LICENSE
multisubprocess/README.md
multisubprocess/__init__.py
multisubprocess/requirements.txt
multisubprocess/thirdparty.json
multisubprocess-0.13.dist-info/LICENSE.rst
multisubprocess-0.13.dist-info/METADATA
multisubprocess-0.13.dist-info/WHEEL
multisubprocess-0.13.dist-info/top_level.txt
multisubprocess-0.13.dist-info/RECORD
