Metadata-Version: 2.1
Name: multisubprocess
Version: 0.13
Summary: Executes multiple subprocesses simultaneously (Windows only)
Home-page: https://github.com/hansalemaos/multisubprocess
Author: Johannes Fischer
Author-email: aulasparticularesdealemaosp@gmail.com
License: MIT
Keywords: subprocess,simultaneously
Classifier: Development Status :: 4 - Beta
Classifier: Programming Language :: Python :: 3 :: Only
Classifier: Programming Language :: Python :: 3.10
Classifier: Topic :: Software Development :: Libraries :: Python Modules
Classifier: Topic :: Utilities
License-File: LICENSE.rst
Requires-Dist: escape-windows-filepath
Requires-Dist: kthread-sleep
Requires-Dist: subprocess-alive
Requires-Dist: subprocesskiller
